romsi_hate_speech/__init__.py
romsi_hate_speech/api.py
romsi_hate_speech/cli.py
romsi_hate_speech/inference_preprocessor.py
romsi_hate_speech/model_loader.py
romsi_hate_speech/predictor.py
romsi_hate_speech-1.0.1.dist-info/licenses/LICENSE
romsi_hate_speech-1.0.1.dist-info/METADATA
romsi_hate_speech-1.0.1.dist-info/WHEEL
romsi_hate_speech-1.0.1.dist-info/entry_points.txt
romsi_hate_speech-1.0.1.dist-info/top_level.txt
romsi_hate_speech-1.0.1.dist-info/RECORD
