Metadata-Version: 2.4
Name: romsi_hate_speech
Version: 1.0.1
Summary: Detect Romanized Sinhala hate speech using mBERT.
Home-page: https://github.com/sakunchamikara/Hate_Speech_Detection_System
Author: Sakun Chamikara
License: MIT
Classifier: Programming Language :: Python :: 3
Classifier: License :: OSI Approved :: MIT License
Classifier: Operating System :: OS Independent
Requires-Python: >=3.7
License-File: LICENSE
Requires-Dist: transformers
Requires-Dist: torch
Requires-Dist: fastapi
Requires-Dist: uvicorn
Requires-Dist: pydantic
Dynamic: author
Dynamic: classifier
Dynamic: description
Dynamic: description-content-type
Dynamic: home-page
Dynamic: license
Dynamic: license-file
Dynamic: requires-dist
Dynamic: requires-python
Dynamic: summary
